walkingliberty/__init__.py
walkingliberty/cli.py
walkingliberty/py.typed
walkingliberty/utilities.py
walkingliberty-0.6.1.dist-info/LICENSE.txt
walkingliberty-0.6.1.dist-info/METADATA
walkingliberty-0.6.1.dist-info/WHEEL
walkingliberty-0.6.1.dist-info/entry_points.txt
walkingliberty-0.6.1.dist-info/top_level.txt
walkingliberty-0.6.1.dist-info/RECORD
