Metadata-Version: 2.1
Name: walkingliberty
Version: 0.6.1
Summary: Basic, stateless wallet using HD type 1.
Author: SporeStack
Author-email: support@sporestack.com
License: Unlicense
Keywords: bitcoin,bitcoincash,bitcoinsv
Requires-Python: >=3.8
License-File: LICENSE.txt
Requires-Dist: bit
Requires-Dist: bitcash (>=0.5.0)
Requires-Dist: bitsv (>=0.9.0)
Requires-Dist: segno
